{
  "id": 73772,
  "level": "organization",
  "elementId": 23,
  "objectName": "my-contact-activities",
  "vendorName": "Event",
  "startDate": "2020-01-28 21:25:12.985751",
  "fields": [
    {
      "type": "string",
      "path": "createdDate",
      "level": "organization",
      "vendorPath": "CreatedDate"
    },
    {
      "type": "string",
      "path": "desc",
      "level": "organization",
      "vendorPath": "Description"
    },
    {
      "type": "string",
      "path": "id",
      "level": "organization",
      "vendorPath": "Id"
    },
    {
      "type": "string",
      "path": "lastModifiedDate",
      "level": "organization",
      "vendorPath": "LastModifiedDate"
    }
  ],
  "configuration": [
    {
      "type": "passThrough",
      "properties": {
        "fromVendor": false,
        "toVendor": false
      }
    },
    {
      "type": "addToDocumentation"
    },
    {
      "type": "inherit"
    }
  ],
  "isLegacy": false
}